maxquery/__init__.py
maxquery/cli.py
maxquery/core.py
maxquery/credentials.py
maxquery-1.0.1.dist-info/licenses/LICENSE
maxquery-1.0.1.dist-info/METADATA
maxquery-1.0.1.dist-info/WHEEL
maxquery-1.0.1.dist-info/entry_points.txt
maxquery-1.0.1.dist-info/top_level.txt
maxquery-1.0.1.dist-info/RECORD
