Metadata-Version: 2.4
Name: maxquery
Version: 1.0.1
Summary: MaxCompute SQL Query Runner - Execute queries on Alibaba Cloud
Home-page: https://github.com/chethanpatel/maxquery
Author: Chethan Patel
Author-email: Chethan Patel <chethanpatel100@gmail.com>
Keywords: maxcompute,odps,sql,alibaba,aliyun,query-runner
Classifier: Programming Language :: Python :: 3
Classifier: Programming Language :: Python :: 3.8
Classifier: Programming Language :: Python :: 3.9
Classifier: Programming Language :: Python :: 3.10
Classifier: Programming Language :: Python :: 3.11
Classifier: License :: OSI Approved :: MIT License
Classifier: Operating System :: OS Independent
Requires-Python: >=3.8
License-File: LICENSE
Requires-Dist: odps==3.5.1
Requires-Dist: pandas==2.3.3
Requires-Dist: python-dotenv==1.2.1
Requires-Dist: pyarrow==23.0.0
Requires-Dist: click>=8.0.0
Requires-Dist: rich>=12.0.0
Provides-Extra: dev
Requires-Dist: pytest>=7.0; extra == "dev"
Requires-Dist: pytest-cov>=3.0; extra == "dev"
Requires-Dist: black>=22.0; extra == "dev"
Requires-Dist: flake8>=4.0; extra == "dev"
Dynamic: author
Dynamic: home-page
Dynamic: license-file
Dynamic: requires-python
